django_msteams_notify/__init__.py
django_msteams_notify/__main__.py
django_msteams_notify/admin.py
django_msteams_notify/apps.py
django_msteams_notify/cli.py
django_msteams_notify/models.py
django_msteams_notify/notify.py
django_msteams_notify/serializers.py
django_msteams_notify/signals.py
django_msteams_notify/tasks.py
django_msteams_notify/urls.py
django_msteams_notify/utils.py
django_msteams_notify/views.py
django_msteams_notify/migrations/0001_initial.py
django_msteams_notify/migrations/0002_auto_20250917_1033.py
django_msteams_notify/migrations/__init__.py
django_msteams_notify-6.0.5.dist-info/licenses/LICENSE
django_msteams_notify-6.0.5.dist-info/METADATA
django_msteams_notify-6.0.5.dist-info/WHEEL
django_msteams_notify-6.0.5.dist-info/entry_points.txt
django_msteams_notify-6.0.5.dist-info/top_level.txt
django_msteams_notify-6.0.5.dist-info/RECORD
