Metadata-Version: 2.4
Name: django-msteams-notify
Version: 6.0.5
Summary: Python Boilerplate contains all the boilerplate you need to create a Python package.
Author-email: Asmita Shah <shahasmita379@gmail.com>
Maintainer-email: Asmita Shah <shahasmita379@gmail.com>
License: MIT
Project-URL: bugs, https://github.com/audreyfeldroy/django_msteams_notify/issues
Project-URL: changelog, https://github.com/audreyfeldroy/django_msteams_notify/blob/master/changelog.md
Project-URL: homepage, https://github.com/audreyfeldroy/django_msteams_notify
Requires-Python: >=3.10
License-File: LICENSE
Requires-Dist: typer
Provides-Extra: test
Requires-Dist: coverage; extra == "test"
Requires-Dist: pytest; extra == "test"
Requires-Dist: ruff; extra == "test"
Requires-Dist: ty; extra == "test"
Requires-Dist: ipdb; extra == "test"
Dynamic: license-file
